molbotomy/__init__.py
molbotomy/cleaning.py
molbotomy/clustering.py
molbotomy/constants.py
molbotomy/descriptors.py
molbotomy/distances.py
molbotomy/evaluate.py
molbotomy/split.py
molbotomy/tools.py
molbotomy/utils.py
molbotomy-0.0.1.dist-info/LICENSE
molbotomy-0.0.1.dist-info/METADATA
molbotomy-0.0.1.dist-info/WHEEL
molbotomy-0.0.1.dist-info/top_level.txt
molbotomy-0.0.1.dist-info/RECORD
