Metadata-Version: 2.1
Name: molbotomy
Version: 0.0.1
Summary: Tool to clean, process, and split molecular data
Home-page: https://github.com/molML/MolBotomy
Author: Derek van Tilborg
Author-email: 
License: MIT
License-File: LICENSE
Requires-Dist: tqdm
Requires-Dist: scipy
Requires-Dist: numpy
Requires-Dist: rdkit
Requires-Dist: levenshtein
